_getoolkit.cpython-37m-x86_64-linux-gnu.so
getoolkit-0.0.6.dist-info/top_level.txt
getoolkit-0.0.6.dist-info/WHEEL
getoolkit-0.0.6.dist-info/METADATA
getoolkit-0.0.6.dist-info/RECORD
getoolkit/app.py
getoolkit/downsample2x.py
getoolkit/__init__.py
getoolkit/generate_mipmaps.py
