Metadata-Version: 2.1
Name: getoolkit
Version: 0.0.6
Summary: getoolkit
Home-page: https://github.com/podgorskiy/getoolkit
Author: Stanislav Pidhorskyi
Author-email: stpidhorskyi@mix.wvu.edu
License: MIT
Keywords: imgui ui
Platform: UNKNOWN
Classifier: Development Status :: 3 - Alpha
Classifier: License :: OSI Approved :: MIT License
Classifier: Programming Language :: Python :: 2.7
Classifier: Programming Language :: Python :: 3.5
Classifier: Programming Language :: Python :: 3.6
Classifier: Programming Language :: Python :: 3.7
Classifier: Programming Language :: Python :: 3.8
